data/__init__.py
data/load_20newsgroups.py
latent_semantic_analysis/__init__.py
latent_semantic_analysis/__main__.py
latent_semantic_analysis/config.py
latent_semantic_analysis/data.py
latent_semantic_analysis/save.py
latent_semantic_analysis/train.py
latent_semantic_analysis/utils.py
tests/__init__.py
tests/test_pipeline.py
latent_semantic_analysis-0.1.0.dist-info/LICENSE
latent_semantic_analysis-0.1.0.dist-info/METADATA
latent_semantic_analysis-0.1.0.dist-info/WHEEL
latent_semantic_analysis-0.1.0.dist-info/entry_points.txt
latent_semantic_analysis-0.1.0.dist-info/top_level.txt
latent_semantic_analysis-0.1.0.dist-info/RECORD
