Metadata-Version: 2.1
Name: latent-semantic-analysis
Version: 0.1.0
Summary: Pipeline for training LSA models using Scikit-Learn.
Home-page: https://github.com/dayyass/latent-semantic-analysis
Author: Dani El-Ayyass
Author-email: dayyass@yandex.ru
License: UNKNOWN
Project-URL: Bug Tracker, https://github.com/dayyass/latent-semantic-analysis/issues
Platform: UNKNOWN
Classifier: Programming Language :: Python :: 3
Classifier: License :: OSI Approved :: MIT License
Classifier: Operating System :: OS Independent
Requires-Python: >=3.6
License-File: LICENSE
Requires-Dist: numpy (>=1.19.5)
Requires-Dist: pandas (>=1.1.5)
Requires-Dist: PyYAML (>=5.4.1)
Requires-Dist: scikit-learn (>=0.24.2)
Requires-Dist: scipy (>=1.5.4)
